Metadata-Version: 2.1
Name: pyperclipimg
Version: 0.2.0
Summary: Cross-platform copy() and paste() Python functions for images.
Home-page: https://github.com/asweigart/pyperclipimg
Author: Al Sweigart
Author-email: al@inventwithpython.com
License: MIT
Classifier: License :: OSI Approved :: MIT License
Classifier: Programming Language :: Python
Classifier: Programming Language :: Python :: 3
Classifier: Programming Language :: Python :: 3.6
Classifier: Programming Language :: Python :: 3.7
Classifier: Programming Language :: Python :: 3.8
Classifier: Programming Language :: Python :: 3.9
Classifier: Programming Language :: Python :: 3.10
Classifier: Programming Language :: Python :: 3.11
Classifier: Programming Language :: Python :: 3.12
Classifier: Programming Language :: Python :: 3.13
License-File: LICENSE
